antonkuzmn1_test/__init__.py
antonkuzmn1_test/py.typed
antonkuzmn1_test/tree.py
antonkuzmn1_test-0.1.0.dist-info/WHEEL
antonkuzmn1_test-0.1.0.dist-info/METADATA
antonkuzmn1_test-0.1.0.dist-info/RECORD
