Metadata-Version: 2.3
Name: antonkuzmn1-test
Version: 0.1.0
Summary: Add your description here
Author: antonkuzmn1
Author-email: antonkuzmn1 <antonkuzmn1@gmail.com>
License: Apache License 2.0
Requires-Dist: uv-build>=0.9.25
Requires-Python: >=3.14
